src/__init__.py
src/constants/__init__.py
src/driver/__init__.py
src/driver/base_driver.py
src/driver/base_smart_tv_driver.py
src/driver/by.py
src/driver/device_capabilities.py
src/driver/element.py
src/driver/finder.py
src/driver/html_by.py
src/driver/options.py
src/driver/proxy.py
src/driver/screen.py
src/driver/screen_size.py
src/driver/screen_text.py
src/driver/server_post_handler.py
src/driver/hdmi/__init__.py
src/driver/hdmi/hdmi_driver.py
src/driver/hdmi/hdmi_remote.py
src/driver/lgwebos/__init__.py
src/driver/lgwebos/lg_webos_driver.py
src/driver/lgwebos/lg_webos_remote.py
src/driver/roku/__init__.py
src/driver/roku/roku_by.py
src/driver/roku/roku_device_info.py
src/driver/roku/roku_driver.py
src/driver/roku/roku_info.py
src/driver/roku/roku_media_player_info.py
src/driver/roku/roku_options.py
src/driver/roku/roku_remote.py
src/driver/roku/roku_screen.py
src/driver/tizentv/__init__.py
src/driver/tizentv/tizen_tv_driver.py
src/driver/tizentv/tizen_tv_remote.py
src/driver/tizentv/tizen_tv_remote_authorizer.py
src/driver/vizio/__init__.py
src/driver/vizio/vizio_driver.py
src/driver/vizio/vizio_remote.py
src/driver/vizio/vizio_remote_authorizer.py
src/driver/xbox/__init__.py
src/driver/xbox/xbox_device_info.py
src/driver/xbox/xbox_driver.py
src/driver/xbox/xbox_info.py
src/driver/xbox/xbox_remote.py
src/enums/__init__.py
src/enums/lg_webos_button.py
src/enums/roku_button.py
src/enums/session_status.py
src/enums/tizen_tv_button.py
src/enums/vizio_button.py
src/enums/xbox_button.py
src/exceptions/__init__.py
src/exceptions/no_such_element_exception.py
src/exceptions/not_authorized_exception.py
src/exceptions/proxy_exception.py
src/exceptions/remote_interact_exception.py
src/exceptions/screen_exception.py
src/exceptions/server_failure_exception.py
src/exceptions/session_not_started_exception.py
src/httpexecutor/__init__.py
src/httpexecutor/http_client.py
src/utils/__init__.py
src/utils/file_to_string_utils.py
rokuality_python-1.5.3.dist-info/LICENSE.txt
rokuality_python-1.5.3.dist-info/METADATA
rokuality_python-1.5.3.dist-info/WHEEL
rokuality_python-1.5.3.dist-info/top_level.txt
rokuality_python-1.5.3.dist-info/RECORD
