Metadata-Version: 2.1
Name: rokuality-python
Version: 1.5.3
Summary: Python bindings for the rokuality platform. End to End Test Automation for Roku, XBox, Vizio, Tizen TV, LG webOS, and HDMI devices including Cable SetTop, Playstation, Tivo and more!
Home-page: https://github.com/rokuality/rokuality-python
Author: rokualitydevs@rokuality.com
Author-email: rokualitydevs@rokuality.com
License: UNKNOWN
Platform: UNKNOWN
Requires-Python: >=3.6.5
Requires-Dist: requests
Requires-Dist: pytest
